textcomplete/__init__.py
textcomplete/example.py
textcomplete/frontend/.npmignore
textcomplete/frontend/.prettierignore
textcomplete/frontend/.prettierrc
textcomplete/frontend/build/index.html
textcomplete/frontend/build/index.js
textcomplete/frontend/eslint.config.js
textcomplete/frontend/jest.config.ts
textcomplete/frontend/package-lock.json
textcomplete/frontend/package.json
textcomplete/frontend/patches/@textcomplete+textarea+0.1.13.patch
textcomplete/frontend/rspack.config.js
textcomplete/frontend/src/helpers.js
textcomplete/frontend/src/index.js
textcomplete/frontend/src/streamlit.d.ts
textcomplete/frontend/src/streamlit.js
textcomplete/test___init__.py
streamlit_textcomplete-0.2.0.dist-info/LICENSE
streamlit_textcomplete-0.2.0.dist-info/METADATA
streamlit_textcomplete-0.2.0.dist-info/WHEEL
streamlit_textcomplete-0.2.0.dist-info/RECORD
