Metadata-Version: 2.1
Name: streamlit-textcomplete
Version: 0.2.0
Summary: Streamlit autocomplete Textcomplete editor for HTMLTextAreaElement
Home-page: https://github.com/voznik/streamlit-textcomplete
License: MIT
Keywords: streamlit,textarea,autocomplete,textcomplete,emoji
Author: voznik
Author-email: mrvoznik@gmail.com
Requires-Python: >=3.10,<4.0
Classifier: License :: OSI Approved :: MIT License
Classifier: Programming Language :: Python :: 3
Classifier: Programming Language :: Python :: 3.10
Classifier: Programming Language :: Python :: 3.11
Classifier: Programming Language :: Python :: 3.12
Classifier: Programming Language :: Python :: 3.13
Requires-Dist: pandas (>=2.2.2,<3.0.0)
Requires-Dist: streamlit (>=1.34.0)
Project-URL: Repository, https://github.com/voznik/streamlit-textcomplete
